LICENSE
MANIFEST.in
Makefile
README.md
pyproject.toml
setup.py
bin/img2video
bin/pyqvarsi_ensi2bin
bin/pyqvarsi_ensi2mpio
bin/pyqvarsi_fixalyapar
bin/pyqvarsi_gmsh2alya
bin/pyqvarsi_h5convert
bin/pyqvarsi_h5mpiopart
bin/pyqvarsi_interpolate
bin/pyqvarsi_mpio2dat
bin/pyqvarsi_mpio2h5
bin/pyqvarsi_mpio2vtkh5
bin/pyqvarsi_mpioheader
bin/pyqvarsi_periodic
bin/pyqvarsi_wit2field
config/options_default.cfg
pyQvarsi/__init__.py
pyQvarsi/checkpoint.py
pyQvarsi/communicator.py
pyQvarsi/cr.py
pyQvarsi/field.py
pyQvarsi/mem.py
pyQvarsi/mesh.py
pyQvarsi/partition_table.py
pyQvarsi.egg-info/PKG-INFO
pyQvarsi.egg-info/SOURCES.txt
pyQvarsi.egg-info/dependency_links.txt
pyQvarsi.egg-info/requires.txt
pyQvarsi.egg-info/top_level.txt
pyQvarsi/FEM/__init__.py
pyQvarsi/FEM/div.py
pyQvarsi/FEM/divgp.py
pyQvarsi/FEM/grad.py
pyQvarsi/FEM/gradgp.py
pyQvarsi/FEM/integral.py
pyQvarsi/FEM/lib.py
pyQvarsi/FEM/mass.py
pyQvarsi/FEM/quadratures.py
pyQvarsi/FEM/utils.py
pyQvarsi/Geom/__init__.py
pyQvarsi/Geom/basic.py
pyQvarsi/Geom/entities.py
pyQvarsi/inp_out/AlyaMPIO.py
pyQvarsi/inp_out/EnsightIO.py
pyQvarsi/inp_out/HiFiTurbReader.py
pyQvarsi/inp_out/HiFiTurbWriter.py
pyQvarsi/inp_out/VTKIO.py
pyQvarsi/inp_out/__init__.py
pyQvarsi/inp_out/h5io.py
pyQvarsi/inp_out/pklio.py
pyQvarsi/inp_out/sod2dIO.py
pyQvarsi/inp_out/vtkh5io.py
pyQvarsi/inp_out/xdmfIO.py
pyQvarsi/meshing/__init__.py
pyQvarsi/meshing/cellcenters.py
pyQvarsi/meshing/interpolate.py
pyQvarsi/meshing/mesh.py
pyQvarsi/meshing/reduction.py
pyQvarsi/periodic/__init__.py
pyQvarsi/periodic/periodic.py
pyQvarsi/plotting/__init__.py
pyQvarsi/plotting/plot_matplotlib.py
pyQvarsi/plotting/plot_pyvista.py
pyQvarsi/postproc/__init__.py
pyQvarsi/postproc/averaging.py
pyQvarsi/postproc/fftspectra.py
pyQvarsi/postproc/vortex_detection.py
pyQvarsi/postproc/yplus.py
pyQvarsi/solvers/__init__.py
pyQvarsi/solvers/approxInverse.py
pyQvarsi/solvers/conjgrad.py
pyQvarsi/solvers/lumped.py
pyQvarsi/statistics/__init__.py
pyQvarsi/statistics/accumulators.py
pyQvarsi/statistics/basic.py
pyQvarsi/statistics/budgets.py
pyQvarsi/statistics/flow_statistics.py
pyQvarsi/utils/__init__.py
pyQvarsi/utils/common.py
