Metadata-Version: 2.2
Name: pyQvarsi
Version: 3.1.0
Summary: Python interface for Alya and other codes
Home-page: https://gitlab.com/ArnauMiro/pyQvarsi.git
Author-email: Benet Eiximeno <benet.eiximeno@bsc.es>, Arnau Miro <arnau.mirojane@bsc.es>, Oriol Lehmkuhl <oriol.lehmkuhl@bsc.es>
Maintainer-email: Benet Eiximeno <benet.eiximeno@bsc.es>, Arnau Miro <arnau.mirojane@bsc.es>
License: MIT License
Project-URL: Homepage, https://ArnauMiro@gitlab.com/ArnauMiro/pyQvarsi
Project-URL: Bug Reports, https://ArnauMiro@gitlab.com/ArnauMiro/pyQvarsi/issues
Project-URL: Source, https://ArnauMiro@gitlab.com/ArnauMiro/pyQvarsi
Keywords: CFD,Alya,post-processing
Classifier: Development Status :: 5 - Production/Stable
Classifier: Intended Audience :: Developers
Classifier: Topic :: Software Development :: Build Tools
Classifier: License :: OSI Approved :: MIT License
Classifier: Programming Language :: Python :: 3
Classifier: Programming Language :: Python :: 3.7
Classifier: Programming Language :: Python :: 3.8
Classifier: Programming Language :: Python :: 3.9
Classifier: Programming Language :: Python :: 3.10
Classifier: Programming Language :: Python :: 3.11
Classifier: Programming Language :: Python :: 3 :: Only
Requires-Python: >=3.7
License-File: LICENSE
Requires-Dist: numpy>=1.21.6
Requires-Dist: scipy>=1.5.4
Requires-Dist: cython>=3.0.0
Requires-Dist: mpi4py>=4.0.0
Requires-Dist: matplotlib
Requires-Dist: nfft
Provides-Extra: full
Requires-Dist: vtk; extra == "full"
Requires-Dist: h5py>=3.0.0; extra == "full"
Requires-Dist: pyvista; extra == "full"
Dynamic: home-page
